{
    "name": "__MSG_extensionName__",
    "description": "__MSG_extensionDescription__",
    "version": "2.8.3",
    "default_locale": "ja",
    "manifest_version": 3,
    "icons": {
        "16": "icon/icon16.png",
        "48": "icon/icon48.png",
        "128": "icon/icon128.png"
    },
    "content_scripts": [
          {
            "matches": [
                "*://*.twitter.com/*"
            ],
            "js": [
                "scr/style.js"
            ]
        }
    ],
    "options_ui": {
        "page":"TUIC/options/options.html",
        "browser_style":true
    },
    "permissions": [
        "tabs",
        "notifications",
        "storage"
    ],
    "action": {
        "default_icon": {
            "16": "icon/icon16.png",
            "48": "icon/icon48.png",
            "128": "icon/icon128.png"
        },
        "default_title": "Twitter UI Customizer",
        "default_popup": "TUIC/popup/popup.html"
    },
    "background":{
        "service_worker":"background.js"
    },
    "host_permissions":[
        "https://github.com/kaonasi-biwa/Twitter-UI-Customizer/releases/latest/download/*",
        "https://objects.githubusercontent.com/*",
        "https://*.mico.re/*"
    ]
}